syft_objects/__init__.py
syft_objects/_validation.py
syft_objects/accessors.py
syft_objects/auto_install.py
syft_objects/clean_api.py
syft_objects/client.py
syft_objects/collections.py
syft_objects/config.py
syft_objects/data_accessor.py
syft_objects/display.py
syft_objects/factory.py
syft_objects/file_ops.py
syft_objects/mock_analyzer.py
syft_objects/models.py
syft_objects/permissions.py
syft_objects/prompts.py
syft_objects/prompts_simple.py
syft_objects/utils.py
syft_objects-0.10.18.dist-info/METADATA
syft_objects-0.10.18.dist-info/WHEEL
syft_objects-0.10.18.dist-info/RECORD
