Metadata-Version: 2.4
Name: syft-objects
Version: 0.10.18
Summary: Share files with explicit mock vs private control
Project-URL: Homepage, https://github.com/OpenMined/syft-objects
Project-URL: Documentation, https://openmined.github.io/syft-objects/
Project-URL: Repository, https://github.com/OpenMined/syft-objects
Project-URL: Bug Tracker, https://github.com/OpenMined/syft-objects/issues
Project-URL: Discussions, https://github.com/OpenMined/syft-objects/discussions
Author-email: OpenMined <contact@openmined.org>
Maintainer-email: OpenMined <contact@openmined.org>
Keywords: data-sharing,distributed,openmined,privacy,syft
Classifier: Development Status :: 4 - Beta
Classifier: Intended Audience :: Developers
Classifier: Intended Audience :: Science/Research
Classifier: License :: OSI Approved :: Apache Software License
Classifier: Operating System :: OS Independent
Classifier: Programming Language :: Python :: 3
Classifier: Programming Language :: Python :: 3.9
Classifier: Programming Language :: Python :: 3.10
Classifier: Programming Language :: Python :: 3.11
Classifier: Programming Language :: Python :: 3.12
Classifier: Topic :: Scientific/Engineering :: Artificial Intelligence
Classifier: Topic :: Software Development :: Libraries :: Python Modules
Classifier: Topic :: System :: Distributed Computing
Requires-Python: >=3.9
Requires-Dist: build>=1.2.2.post1
Requires-Dist: fastapi>=0.104.0
Requires-Dist: httptools>=0.6.0
Requires-Dist: loguru>=0.7.0
Requires-Dist: pydantic>=2.0.0
Requires-Dist: python-multipart>=0.0.20
Requires-Dist: pyyaml>=6.0
Requires-Dist: requests>=2.32.4
Requires-Dist: syft-core>=0.2.5
Requires-Dist: syft-perm>=0.1.0
Requires-Dist: twine>=6.1.0
Requires-Dist: uvicorn[standard]>=0.24.0
Requires-Dist: uvloop>=0.17.0; sys_platform != 'win32'
Provides-Extra: data
Requires-Dist: numpy>=1.20.0; extra == 'data'
Requires-Dist: openpyxl>=3.0.0; extra == 'data'
Requires-Dist: pandas>=2.0.0; extra == 'data'
Requires-Dist: pyarrow>=10.0.0; extra == 'data'
Provides-Extra: dev
Requires-Dist: black>=23.0.0; extra == 'dev'
Requires-Dist: isort>=5.0.0; extra == 'dev'
Requires-Dist: mypy>=1.0.0; extra == 'dev'
Requires-Dist: pre-commit>=3.0.0; extra == 'dev'
Requires-Dist: pytest-cov>=4.0.0; extra == 'dev'
Requires-Dist: pytest>=7.0.0; extra == 'dev'
Provides-Extra: docs
Requires-Dist: mkdocs-jupyter>=0.24.0; extra == 'docs'
Requires-Dist: mkdocs-material>=9.0.0; extra == 'docs'
Requires-Dist: mkdocs>=1.5.0; extra == 'docs'
